py_mscip/__init__.py
py_mscip/commands/__init__.py
py_mscip/commands/base_commands.py
py_mscip/commands/imu_commands.py
py_mscip/interfaces/__init__.py
py_mscip/interfaces/config.py
py_mscip/interfaces/conn.py
py_mscip/interfaces/imu.py
py_mscip/packets/__init__.py
py_mscip/packets/cip.py
py_mscip/packets/cip_parser.py
py_mscip/packets/il_parser.py
py_mscip/packets/packet.py
py_mscip/packets/packet_factory.py
py_mscip-0.1.0.dist-info/METADATA
py_mscip-0.1.0.dist-info/WHEEL
py_mscip-0.1.0.dist-info/top_level.txt
py_mscip-0.1.0.dist-info/RECORD
