Metadata-Version: 2.1
Name: py-mscip
Version: 0.1.0
Summary: Library interface for communication with Memsense IMU devices
Home-page: https://gitlab.com/memsense/py_mscip
Author: Memsense
Author-email: nneisen@memsense.com
License: UNKNOWN
Platform: UNKNOWN
Classifier: Programming Language :: Python :: 3
Requires-Python: >=3.6
